microstructural_lick_analysis/extract_params.py
microstructural_lick_analysis/summarize_data.py
microstructural_lick_analysis-0.1.dist-info/DESCRIPTION.rst
microstructural_lick_analysis-0.1.dist-info/METADATA
microstructural_lick_analysis-0.1.dist-info/RECORD
microstructural_lick_analysis-0.1.dist-info/WHEEL
microstructural_lick_analysis-0.1.dist-info/metadata.json
microstructural_lick_analysis-0.1.dist-info/top_level.txt
