Metadata-Version: 2.0
Name: microstructural-lick-analysis
Version: 0.1
Summary: Analyzes and calculates lick data.
Home-page: https://github.com/pungaliy/Microstructural_Lick_Analysis.git
Author: Shray Pungaliya, Katrina Chandra
Author-email: kbchandr@usc.com
License: UNKNOWN
Platform: UNKNOWN
